numpyascii_GonenRaveh/__init__.py
numpyascii_GonenRaveh/numpyascii.py
numpyascii_package_GonenRaveh-1.0.5.dist-info/LICENSE
numpyascii_package_GonenRaveh-1.0.5.dist-info/METADATA
numpyascii_package_GonenRaveh-1.0.5.dist-info/WHEEL
numpyascii_package_GonenRaveh-1.0.5.dist-info/top_level.txt
numpyascii_package_GonenRaveh-1.0.5.dist-info/RECORD
