Metadata-Version: 2.1
Name: numpyascii_package_GonenRaveh
Version: 1.0.5
Summary: Helper Python packages for 1D, 2D and 3D numpy matrices
Author-email: Gonen Raveh <gonen.raveh@gmail.com>
License: Copyright (c) 2018 The Python Packaging Authority
Project-URL: Homepage, https://github.com/gonenraveh/numpyascii
Classifier: Programming Language :: Python :: 3
Classifier: License :: OSI Approved :: MIT License
Classifier: Operating System :: OS Independent
Requires-Python: >=3.8
License-File: LICENSE
Requires-Dist: numpy
